README.txt
bootstrap.py
buildout.cfg
setup.py
src/gocept/__init__.py
src/gocept.mochikit.egg-info/PKG-INFO
src/gocept.mochikit.egg-info/SOURCES.txt
src/gocept.mochikit.egg-info/dependency_links.txt
src/gocept.mochikit.egg-info/namespace_packages.txt
src/gocept.mochikit.egg-info/not-zip-safe
src/gocept.mochikit.egg-info/requires.txt
src/gocept.mochikit.egg-info/top_level.txt
src/gocept/mochikit/__init__.py
src/gocept/mochikit/configure.zcml
src/gocept/mochikit/ftesting.zcml
src/gocept/mochikit/interfaces.py
src/gocept/mochikit/libraries.zcml
src/gocept/mochikit/tests.py
src/gocept/mochikit/unpacked.zcml
src/gocept/mochikit/viewletmanager.txt
src/gocept/mochikit/zope2.zcml
src/gocept/mochikit/resources/base.js
src/gocept/mochikit/resources/close.png
src/gocept/mochikit/resources/jsclass.js
src/gocept/mochikit/resources/lightbox.css
src/gocept/mochikit/resources/lightbox.js
src/gocept/mochikit/resources/MochiKit-1.4.2/Changes
src/gocept/mochikit/resources/MochiKit-1.4.2/LICENSE.txt
src/gocept/mochikit/resources/MochiKit-1.4.2/MANIFEST
src/gocept/mochikit/resources/MochiKit-1.4.2/META.json
src/gocept/mochikit/resources/MochiKit-1.4.2/doc/html/MochiKit/Async.html
src/gocept/mochikit/resources/MochiKit-1.4.2/doc/html/MochiKit/Base.html
src/gocept/mochikit/resources/MochiKit-1.4.2/doc/html/MochiKit/Color.html
src/gocept/mochikit/resources/MochiKit-1.4.2/doc/html/MochiKit/DOM.html
src/gocept/mochikit/resources/MochiKit-1.4.2/doc/html/MochiKit/DateTime.html
src/gocept/mochikit/resources/MochiKit-1.4.2/doc/html/MochiKit/DragAndDrop.html
src/gocept/mochikit/resources/MochiKit-1.4.2/doc/html/MochiKit/Format.html
src/gocept/mochikit/resources/MochiKit-1.4.2/doc/html/MochiKit/Iter.html
src/gocept/mochikit/resources/MochiKit-1.4.2/doc/html/MochiKit/Logging.html
src/gocept/mochikit/resources/MochiKit-1.4.2/doc/html/MochiKit/LoggingPane.html
src/gocept/mochikit/resources/MochiKit-1.4.2/doc/html/MochiKit/Position.html
src/gocept/mochikit/resources/MochiKit-1.4.2/doc/html/MochiKit/Selector.html
src/gocept/mochikit/resources/MochiKit-1.4.2/doc/html/MochiKit/Signal.html
src/gocept/mochikit/resources/MochiKit-1.4.2/doc/html/MochiKit/Sortable.html
src/gocept/mochikit/resources/MochiKit-1.4.2/doc/html/MochiKit/Style.html
