Metadata-Version: 1.0
Name: gocept.mochikit
Version: 1.4.2.3
Summary: MochiKit integration into Zope 3
Home-page: http://pypi.python.org/pypi/gocept.mochikit
Author: Christian Zagrodnick
Author-email: cz@gocept.com
License: ZPL 2.1
Platform: UNKNOWN
